README.md
setup.cfg
setup.py
distributions/Binomialdistribution.py
distributions/Gaussiandistribution.py
distributions/Generaldistribution.py
distributions/__init__.py
szarir_dev_distributions.egg-info/PKG-INFO
szarir_dev_distributions.egg-info/SOURCES.txt
szarir_dev_distributions.egg-info/dependency_links.txt
szarir_dev_distributions.egg-info/not-zip-safe
szarir_dev_distributions.egg-info/top_level.txt